pytest_flake8dir/__init__.py
pytest_flake8dir/py.typed
pytest_flake8dir-2.6.1.dist-info/LICENSE
pytest_flake8dir-2.6.1.dist-info/METADATA
pytest_flake8dir-2.6.1.dist-info/WHEEL
pytest_flake8dir-2.6.1.dist-info/entry_points.txt
pytest_flake8dir-2.6.1.dist-info/top_level.txt
pytest_flake8dir-2.6.1.dist-info/RECORD
